hyperdock_fileio/__init__.py
hyperdock_fileio/directory.py
hyperdock_fileio/operations.py
hyperdock_fileio/read.py
hyperdock_fileio/write.py
hyperdock_fileio/tests/__init__.py
hyperdock_fileio/tests/directory_test.py
hyperdock_fileio/tests/operations_test.py
hyperdock_fileio/tests/read_test.py
hyperdock_fileio/tests/write_test.py
hyperdock_fileio-0.5.7.dist-info/METADATA
hyperdock_fileio-0.5.7.dist-info/WHEEL
hyperdock_fileio-0.5.7.dist-info/top_level.txt
hyperdock_fileio-0.5.7.dist-info/RECORD
