Metadata-Version: 2.4
Name: hyperdock-fileio
Version: 0.5.7
Summary: hyperdockt-fileio
Author-email: Hyperpocket Team <hyperpocket@vessl.ai>
Requires-Python: >=3.10
Requires-Dist: chardet>=5.2.0
Requires-Dist: pytest>=8.3.4
